setup.py
pipecli/__init__.py
pipecli/version.py
pipecli.egg-info/PKG-INFO
pipecli.egg-info/SOURCES.txt
pipecli.egg-info/dependency_links.txt
pipecli.egg-info/entry_points.txt
pipecli.egg-info/requires.txt
pipecli.egg-info/top_level.txt
pipecli/command/__init__.py
pipecli/command/beiguo.py
pipecli/command/cli.py