Metadata-Version: 2.1
Name: pipecli
Version: 0.0.6
Summary: pipecli 流水线命令行
Home-page: https://gitee.com/zhys513/pipecli
Author: zhys513
Author-email: 254851907@qq.com
License: UNKNOWN
Platform: UNKNOWN
Requires-Python: >=3.6
